{"cameraMode":{"drawMode":0,"name":"Shaded","section":"Shading Mode"},"sceneLighting":false,"audioPlay":false,"sceneViewState":{"m_AlwaysRefresh":false,"showFog":true,"showSkybox":false,"showFlares":true,"showImageEffects":true,"showParticleSystems":true,"showVisualEffectGraphs":true,"m_FxEnabled":true},"in2DMode":false,"pivot":{"x":-1.4987969398498536,"y":0.12342901527881623,"z":2.510826587677002},"rotation":{"x":-0.1562371402978897,"y":0.33378225564956667,"z":-0.056206122040748599,"w":-0.9279302358627319},"size":5.197897911071777,"orthographic":false}